EntroPy/EntroPy.py
EntroPy/__init__.py
EntroPy_Package-1.0.1.dist-info/LICENSE
EntroPy_Package-1.0.1.dist-info/METADATA
EntroPy_Package-1.0.1.dist-info/WHEEL
EntroPy_Package-1.0.1.dist-info/top_level.txt
EntroPy_Package-1.0.1.dist-info/RECORD
