Metadata-Version: 2.1
Name: EntroPy-Package
Version: 1.0.1
Summary: A Python package for calculating various forms of entropy.
Home-page: https://github.com/nicolasmcnair/EntroPy
Author: Nicolas McNair
Author-email: nicolas.mcnair@sydney.edu.au
License: UNKNOWN
Keywords: Entropy Information Probability
Platform: UNKNOWN
Classifier: Development Status :: 5 - Production/Stable
Classifier: License :: OSI Approved :: GNU General Public License v3 (GPLv3)
Classifier: Programming Language :: Python :: 2.7
Classifier: Programming Language :: Python :: 3
Requires-Python: >=2.7, !=3.0.*, !=3.1.*, !=3.2.*
Requires-Dist: numpy
Requires-Dist: scipy
